antigranular/__init__.py
antigranular/client.py
antigranular/config/config.py
antigranular/jupyter_client/jupyter_client.py
antigranular/magics/errors.py
antigranular/magics/magics.py
antigranular/models/__init__.py
antigranular/models/models.py
antigranular/utils/error_print.py
antigranular/utils/loading_animation.py
antigranular/utils/print_request_id.py
antigranular-1.0.2.dist-info/LICENSE
antigranular-1.0.2.dist-info/METADATA
antigranular-1.0.2.dist-info/WHEEL
antigranular-1.0.2.dist-info/RECORD
