Metadata-Version: 2.3
Name: antigranular
Version: 1.0.2
Summary: Antigranular is a community-driven, open-source platform that merges remote data science and differential privacy. This creates a secure environment for handling and unlocking the full potential of unseen data..
Author: Oblivious Software
Author-email: support@oblivious.ai
Requires-Python: >=3.9,<4.0
Classifier: Programming Language :: Python :: 3
Classifier: Programming Language :: Python :: 3.9
Classifier: Programming Language :: Python :: 3.10
Classifier: Programming Language :: Python :: 3.11
Classifier: Programming Language :: Python :: 3.12
Classifier: Programming Language :: Python :: 3.13
Provides-Extra: ml-frameworks
Requires-Dist: ipython (>=7.34.0,<8.0.0)
Requires-Dist: numpy (==2.0.2)
Requires-Dist: onnx (==1.16.0)
Requires-Dist: pandas (==2.2.2)
Requires-Dist: pydantic (==2.11.2)
Requires-Dist: requests (>=2.31.0,<3.0.0)
Requires-Dist: torch (>=1.10.0,<2.0.0) ; extra == "ml-frameworks"
